{
  "cookies": "buvid3=8B57D3BA-607A-1E85-018A-E8C430023CED42659infoc; b_lsid=BEB8EE7F_18742FF8C2E; bsource=search_baidu; _uuid=DE810E367-B52C-AF6E-A612-EDF4C31567F358591infoc; b_nut=100; buvid_fp=711a632b5c876fa8bbcf668c1efba551; SESSDATA=7624af93%2C1696008331%2C862c8%2A42; bili_jct=141a474ef3ce8cf2fedf384e68f6625d; DedeUserID=3493271303096985; DedeUserID__ckMd5=212a836c164605b7; sid=5h4ruv6o; buvid4=978E9208-13DA-F87A-3DC0-0B8EDF46E80434329-123040301-dWliG5BMrUb70r3g583u7w%3D%3D",
  "classes": [
    {
      "type_name": "少儿动画",
      "type_id": "少儿动画"
    },
    {
      "type_name": "数码测评",
      "type_id": "数码测评"
    },
    {
      "type_name": "电影解说",
      "type_id": "电影解说"
    },
    {
      "type_name": "沙雕动画",
      "type_id": "沙雕动画"
    },
    {
      "type_name": "中医药",
      "type_id": "中医药"
    },
    {
      "type_name": "戏曲",
      "type_id": "京剧"
    },
    {
      "type_name": "减肥健美操",
      "type_id": "减肥健美操"
    }
  ],
  "filters": {
    "中医药": [
      {
        "key": "tid",
        "name": "分类",
        "value": [
          {
            "n": "中医基础",
            "v": "中医基础"
          },
          {
            "n": "中药基础",
            "v": "中药基础"
          },
          {
            "n": "伤寒论",
            "v": "伤寒论"
          },
          {
            "n": "难经",
            "v": "难经"
          },
          {
            "n": "神农本草经",
            "v": "神农本草经"
          },
          {
            "n": "金匮要略",
            "v": "金匮要略"
          },
          {
            "n": "脉经",
            "v": "脉经"
          },
          {
            "n": "中藏经",
            "v": "中藏经"
          },
          {
            "n": "针灸甲乙经",
            "v": "针灸甲乙经"
          },
          {
            "n": "濒湖脉学",
            "v": "濒湖脉学"
          },
          {
            "n": "本草纲目",
            "v": "本草纲目"
          },
          {
            "n": "汤头歌诀",
            "v": "汤头歌诀"
          },
          {
            "n": "药性赋",
            "v": "药性赋"
          }
        ]
      }
    ],
    "京剧": [
      {
        "key": "tid",
        "name": "分类",
        "value": [
          {
            "n": "京剧",
            "v": "京剧超清"
          },
          {
            "n": "越剧",
            "v": "越剧超清"
          },
          {
            "n": "蒲剧",
            "v": "蒲剧超清"
          },
          {
            "n": "眉户",
            "v": "眉户超清"
          },
          {
            "n": "吕剧",
            "v": "吕剧超清"
          },
          {
            "n": "楚剧",
            "v": "楚剧超清"
          },
          {
            "n": "歌仔戏",
            "v": "歌仔戏超清"
          },
          {
            "n": "黄梅戏",
            "v": "黄梅戏超清"
          },
          {
            "n": "评剧",
            "v": "评剧超清"
          },
          {
            "n": "豫剧",
            "v": "豫剧超清"
          },
          {
            "n": "花鼓戏",
            "v": "花鼓戏超清"
          },
          {
            "n": "布袋戏",
            "v": "布袋戏合集超清"
          },
          {
            "n": "沪剧",
            "v": "沪剧超清"
          },
          {
            "n": "昆曲",
            "v": "昆曲超清"
          },
          {
            "n": "潮剧",
            "v": "潮剧超清"
          },
          {
            "n": "超清潮剧",
            "v": "超清潮剧超清"
          },
          {
            "n": "百花潮剧院",
            "v": "百花潮剧院超清"
          },
          {
            "n": "香港潮剧",
            "v": "香港潮剧超清"
          },
          {
            "n": "潮剧院",
            "v": "潮剧院超清"
          },
          {
            "n": "潮剧团",
            "v": "潮剧团超清"
          },
          {
            "n": "潮剧全剧",
            "v": "潮剧全剧超清"
          },
          {
            "n": "潮剧选段",
            "v": "潮剧选段超清"
          },
          {
            "n": "名家潮剧",
            "v": "名家潮剧超清"
          },
          {
            "n": "潮汕小品",
            "v": "潮汕小品超清"
          },
          {
            "n": "潮汕讲古",
            "v": "潮汕讲古超清"
          },
          {
            "n": "绍兴莲花落",
            "v": "绍兴莲花落超清"
          },
          {
            "n": "河北梆子",
            "v": "河北梆子超清"
          },
          {
            "n": "梆子腔",
            "v": "梆子腔超清"
          },
          {
            "n": "晋剧",
            "v": "晋剧超清"
          },
          {
            "n": "龙江剧",
            "v": "龙江剧超清"
          },
          {
            "n": "越调",
            "v": "越调超清"
          },
          {
            "n": "河南曲剧",
            "v": "河南曲剧超清"
          },
          {
            "n": "山东梆子",
            "v": "山东梆子超清"
          },
          {
            "n": "淮剧",
            "v": "淮剧超清"
          },
          {
            "n": "滑稽戏",
            "v": "滑稽戏超清"
          },
          {
            "n": "婺剧",
            "v": "婺剧超清"
          },
          {
            "n": "绍剧",
            "v": "绍剧超清"
          },
          {
            "n": "徽剧",
            "v": "徽剧超清"
          },
          {
            "n": "雁剧",
            "v": "雁剧超清"
          },
          {
            "n": "上党梆子",
            "v": "上党梆子超清"
          },
          {
            "n": "秦腔",
            "v": "秦腔超清"
          },
          {
            "n": "武安平调",
            "v": "武安平调超清"
          },
          {
            "n": "二人台",
            "v": "二人台超清"
          },
          {
            "n": "吉剧",
            "v": "吉剧超清"
          },
          {
            "n": "高腔",
            "v": "高腔超清"
          }
        ]
      }
    ]
  }
}